setup.py
hcrm_sdk_core.egg-info/PKG-INFO
hcrm_sdk_core.egg-info/SOURCES.txt
hcrm_sdk_core.egg-info/dependency_links.txt
hcrm_sdk_core.egg-info/entry_points.txt
hcrm_sdk_core.egg-info/not-zip-safe
hcrm_sdk_core.egg-info/requires.txt
hcrm_sdk_core.egg-info/top_level.txt
hcrmsdkcore/__init__.py
hcrmsdkcore/Client/Client.py
hcrmsdkcore/Client/__init__.py
hcrmsdkcore/General/General.py
hcrmsdkcore/General/__init__.py
hcrmsdkcore/Sign/Sign.py
hcrmsdkcore/Sign/__init__.py
hcrmsdkcore/exception/__init__.py
hcrmsdkcore/exception/exceptions.py