Metadata-Version: 1.0
Name: hcrm-sdk-core
Version: 1.0
Summary: tal hcrm python3 sdk
Home-page: https://github.com/feeir
Author: tianpengfei
Author-email: 54587841@qq.com
License: UNKNOWN
Keywords: python english translation dictionary terminal
Platform: UNKNOWN
